{
	"name": "Escena 2",
	"layers": [
		{
			"name": "Capa 0",
			"overriden": 0,
			"subLayers": [],
			"instances": [
				{
					"type": "Respuesta_Incorrecta_2",
					"properties": {
						"type": "button",
						"text": "",
						"tooltip": "",
						"initially-visible": true,
						"enabled": true,
						"auto-font-size": true,
						"checked": false,
						"id": "",
						"class": ""
					},
					"uid": 10,
					"instanceVariables": {},
					"behaviors": {},
					"world": {
						"x": 397,
						"y": 323,
						"width": 23.416282435249286,
						"height": 22.132104449640224,
						"originX": 0,
						"originY": 0,
						"color": [
							1,
							1,
							1,
							1
						]
					}
				},
				{
					"type": "Respuesta_Incorrecta_1",
					"properties": {
						"type": "button",
						"text": "",
						"tooltip": "",
						"initially-visible": true,
						"enabled": true,
						"auto-font-size": true,
						"checked": false,
						"id": "",
						"class": ""
					},
					"uid": 11,
					"instanceVariables": {},
					"behaviors": {},
					"world": {
						"x": 444,
						"y": 322,
						"width": 26.010752458630293,
						"height": 21.198156674460336,
						"originX": 0,
						"originY": 0,
						"color": [
							1,
							1,
							1,
							0
						]
					}
				},
				{
					"type": "pixilframe0_2_2",
					"properties": {
						"initially-visible": true,
						"initial-animation": "Default",
						"initial-frame": 0,
						"enable-collisions": true,
						"live-preview": false
					},
					"uid": 12,
					"instanceVariables": {},
					"behaviors": {},
					"world": {
						"x": 427,
						"y": 242,
						"width": 854,
						"height": 480,
						"originX": 0.5,
						"originY": 0.5,
						"color": [
							1,
							1,
							1,
							1
						],
						"angle": 0,
						"zElevation": 0
					}
				},
				{
					"type": "Respuesta_Correcta",
					"properties": {
						"type": "button",
						"text": " ",
						"tooltip": "",
						"initially-visible": true,
						"enabled": true,
						"auto-font-size": true,
						"checked": false,
						"id": "",
						"class": ""
					},
					"uid": 16,
					"instanceVariables": {},
					"behaviors": {},
					"world": {
						"x": 353,
						"y": 324,
						"width": 21.482334660069398,
						"height": 21,
						"originX": 0,
						"originY": 0,
						"color": [
							1,
							1,
							1,
							0
						]
					}
				}
			],
			"sid": 534753738406435,
			"effectTypes": [],
			"isInitiallyVisible": true,
			"isInitiallyInteractive": true,
			"color": [
				1,
				1,
				1,
				1
			],
			"backgroundColor": [
				0.3686274509803922,
				0.3686274509803922,
				0.3686274509803922,
				1
			],
			"isTransparent": false,
			"parallaxX": 1,
			"parallaxY": 1,
			"scaleRate": 1,
			"forceOwnTexture": false,
			"renderingMode": "3d",
			"drawOrder": "z-order",
			"useRenderCells": false,
			"blendMode": "normal",
			"zElevation": 0,
			"global": false
		}
	],
	"sid": 315930842704848,
	"nonworld-instances": [],
	"effectTypes": [],
	"width": 1708,
	"height": 960,
	"unboundedScrolling": false,
	"vpX": 0.5,
	"vpY": 0.5,
	"projection": "perspective",
	"eventSheet": "Hoja de eventos 2"
}